UI/__init__.py
UI/__main__.py
UI/ui_server.py
UI/helpers/__init__.py
UI/helpers/add_new_model.py
UI/helpers/configuration.py
UI/helpers/create_new_version.py
UI/helpers/db_record_to_dictionary.py
UI/helpers/get_model_versions_static_data.py
UI/helpers/get_models_list.py
UI/helpers/model_naming.py
UI/helpers/packer.py
UI/helpers/random_string.py
UI/helpers/remove_model.py
UI/helpers/restore_file.py
UI/helpers/scan_folder.py
UI/helpers/set_model_version_active.py
UI/helpers/set_new_deploy_destination.py
UI/helpers/update_metadata_and_deployables.py
RhythmicML-0.0.1.dist-info/LICENCE.txt
RhythmicML-0.0.1.dist-info/METADATA
RhythmicML-0.0.1.dist-info/WHEEL
RhythmicML-0.0.1.dist-info/top_level.txt
RhythmicML-0.0.1.dist-info/RECORD
